ingenia/__init__.py
ingenia/dataset.py
ingenia/ingenia.py
ingenia/modules/__init__.py
ingenia/modules/agent.py
ingenia/modules/base.py
ingenia/modules/chat.py
ingenia/modules/chunk.py
ingenia/modules/dataset.py
ingenia/modules/document.py
ingenia/modules/session.py
ingenia-0.3.4.dist-info/METADATA
ingenia-0.3.4.dist-info/WHEEL
ingenia-0.3.4.dist-info/RECORD
